download_xml/__init__.py
download_xml/client.py
download_xml-0.1.0.dist-info/METADATA
download_xml-0.1.0.dist-info/WHEEL
download_xml-0.1.0.dist-info/RECORD
