Metadata-Version: 2.1
Name: download-xml
Version: 0.1.0
Summary: 
Author: Fritz Henrique
Author-email: fritzhenrique.dev@gmail.com
Requires-Python: >=3.12,<4.0
Classifier: Programming Language :: Python :: 3
Classifier: Programming Language :: Python :: 3.12
Requires-Dist: aiofiles (>=24.1.0,<25.0.0)
Requires-Dist: aiohttp (>=3.9.5,<4.0.0)
